worldcoinindex/__init__.py
worldcoinindex/client.py
worldcoinindex/constants.py
worldcoinindex-1.0.1.dist-info/LICENSE
worldcoinindex-1.0.1.dist-info/METADATA
worldcoinindex-1.0.1.dist-info/WHEEL
worldcoinindex-1.0.1.dist-info/top_level.txt
worldcoinindex-1.0.1.dist-info/RECORD
