Metadata-Version: 2.1
Name: worldcoinindex
Version: 1.0.1
Summary: A lightweight wrapper for the WorldCoinIndex Cyptocoin API
Home-page: https://www.worldcoinindex.com/apiservice
Author: Pranav Chaturvedi
Author-email: pranavhfs1@gmail.com
Maintainer: PranavChaturvedi
License: MIT
Project-URL: Homepage, https://www.worldcoinindex.com/apiservice
Project-URL: Documentation, https://github.com/PranavChaturvedi/worldcoinindex/blob/main/README.md
Project-URL: Repository, https://github.com/PranavChaturvedi/worldcoinindex
Classifier: Intended Audience :: Developers
Classifier: License :: OSI Approved :: MIT License
Classifier: Programming Language :: Python :: 3.12
Classifier: Programming Language :: Python :: 3.11
Classifier: Programming Language :: Python :: 3.10
Classifier: Programming Language :: Python :: 3.9
Classifier: Programming Language :: Python :: 3.8
Classifier: Topic :: Software Development :: Libraries :: Python Modules
Classifier: Topic :: Utilities
Requires-Python: >=3.8
License-File: LICENSE
